pixyverse/__init__.py
pixyverse/pixy/__init__.py
pixyverse/pixy/__main__.py
pixyverse/pixy/_version.py
pixyverse/pixy/cli.py
pixyverse/pixy/genparser.py
pixyverse/pixy/parser.py
pixyverse/pixy/py.typed
pixyverse/pixy/transpile.py
pixyverse/pixy/grammar/__init__.py
pixyverse/pixy/grammar/pypixie.gram
pixyverse.pixy-0.0.8.dist-info/LICENSE
pixyverse.pixy-0.0.8.dist-info/METADATA
pixyverse.pixy-0.0.8.dist-info/NOTICE
pixyverse.pixy-0.0.8.dist-info/WHEEL
pixyverse.pixy-0.0.8.dist-info/entry_points.txt
pixyverse.pixy-0.0.8.dist-info/top_level.txt
pixyverse.pixy-0.0.8.dist-info/RECORD
